geojson2kml/__init__.py
geojson2kml/__main__.py
geojson2kml/buildkml.py
geojson2kml/cli.py
geojson2kml/version.py
geojson2kml-0.2.0.dist-info/entry_points.txt
geojson2kml-0.2.0.dist-info/LICENSE
geojson2kml-0.2.0.dist-info/WHEEL
geojson2kml-0.2.0.dist-info/METADATA
geojson2kml-0.2.0.dist-info/RECORD
