Metadata-Version: 2.1
Name: geojson2kml
Version: 0.2.0
Summary: Convert GeoJSON to KML file 
Keywords: geojson,KML
Author-email: Alex Guinman <alex@guinman.id.au>
Requires-Python: >=3.8
Classifier: License :: OSI Approved :: MIT License
Classifier: Programming Language :: Python :: 3
Classifier: Programming Language :: Python :: 3.11
Classifier: Programming Language :: Python :: 3.10
Classifier: Programming Language :: Python :: 3.9
Classifier: Operating System :: OS Independent
Requires-Dist: typer
Requires-Dist: simplekml
Requires-Dist: geojson
Requires-Dist: black ; extra == "dev"
Requires-Dist: flake8 ; extra == "dev"
Requires-Dist: flake8-bugbear ; extra == "dev"
Requires-Dist: pep8-naming ; extra == "dev"
Requires-Dist: flake8-builtins ; extra == "dev"
Requires-Dist: pytest >=2.7.3 ; extra == "test"
Requires-Dist: pytest-cov ; extra == "test"
Requires-Dist: mypy ; extra == "test"
Project-URL: Source, https://github.com/aguinane/geojson-to-kml
Provides-Extra: dev
Provides-Extra: test
